{
   "files": [    



{
         "name": "OPENLAND-01-AIS"
         "url": "https://raw.githubusercontent.com/Popeye567/thai/main/OPENLAND-01-AIS.ovpn"
      }
,
{
         "name": "OPENLAND-01-DTAC"
         "url": "https://raw.githubusercontent.com/Popeye567/thai/main/OPENLAND-01-DTAC.ovpn"
      }
,
{
         "name": "OPENLAND-01-TRUE"
         "url": "https://raw.githubusercontent.com/Popeye567/thai/main/OPENLAND-01-TRUE.ovpn"
      }


   ],
"message":"
*🌎- ระบบอัพเดทอัตโนมัติ -🌎
 🆙 อัพเดท วันที่ 10-04-2023


🌟ท่านไดสนใจเช่าVIPเร็วจ๊วด🌟

❤เช่าvipกด❤👇

⚡https://thvpnzx.shop/servers⚡
 
\n\nUpdate:1",
"title":"เวอร์ชั่นที่" ,
   "version":3
}
